URBasic/__init__.py
URBasic/connectionState.py
URBasic/dashboard.py
URBasic/manipulation.py
URBasic/realTimeClient.py
URBasic/register_reset_test.py
URBasic/robotConnector.py
URBasic/robotModel.py
URBasic/rtde.py
URBasic/rtdeConfigurationDefault.xml
URBasic/urScript.py
URBasic/urScriptExt.py
mseep_nonead_universal_robots_mcp-0.1.1.dist-info/licenses/LICENSE
nonead_universal_robots_mcp/nonead_universal_robots_mcp/__init__.py
nonead_universal_robots_mcp/nonead_universal_robots_mcp/server.py
mseep_nonead_universal_robots_mcp-0.1.1.dist-info/METADATA
mseep_nonead_universal_robots_mcp-0.1.1.dist-info/WHEEL
mseep_nonead_universal_robots_mcp-0.1.1.dist-info/entry_points.txt
mseep_nonead_universal_robots_mcp-0.1.1.dist-info/top_level.txt
mseep_nonead_universal_robots_mcp-0.1.1.dist-info/RECORD
